spotflock_studio-1.1.0.dist-info/METADATA
spotflock_studio-1.1.0.dist-info/RECORD
spotflock_studio-1.1.0.dist-info/WHEEL
spotflock_studio-1.1.0.dist-info/top_level.txt
studio/__init__.py
studio/core.py
