Metadata-Version: 2.1
Name: spotflock-studio
Version: 1.1.0
Summary: Python Client for Spotflock Studio.
Home-page: https://github.com/Spotflock/studio-sdk-python
Author: Spotflock LLC
Author-email: connect@spotflock.com
License: UNKNOWN
Platform: UNKNOWN
Classifier: Programming Language :: Python :: 3
Classifier: License :: OSI Approved :: MIT License
Classifier: Operating System :: OS Independent
